[
    
    {   "time":"731",
        "event":["是时，玄宗颇任宦官，高力士尤得宠信，四方表奏，皆先呈力士，往往决之，权倾内外。"],
        "libai":[["在长安期间所见所闻，多有不平，益增感慨。作《古风之二十四》",
                "因屡逢踬碍，备受蹭蹬之苦，对李唐王朝大为失望，乃借蜀道之艰险，状世途之坎坷，抒胸中之愤懑，作《蜀道难》"]],
        "poem":["《古风之二十四》","《蜀道难》"],
        "num":2
    }
    ,{  "time":"735",
        "event":["玄宗令天下士人，其才有霸王之略、学究天人之际，及堪为将帅牧宰者，五品以上官吏各举一人"],
        "libai":[["秋，在太原送人赴京应举，作《秋日于太原南栅饯阳曲王赞公贾少公石艾尹少公应举赴上都序》"]],
        "poem":["《秋日于太原南栅饯阳曲王赞公贾少公石艾尹少公应举赴上都序》"],
        "num":1
    }
    ,{	"time":"742",
        "event":["正月，改元，大赦天下。并诏令：“前资官及白身人有儒学博通、文辞英秀及军谋武艺者，所在县以名荐京。”"],
        "libai":[["玄宗召入京，遂返南陵，作《为宋中丞自荐表》",
                "秋，受诏赴京，作《南陵别儿童入京》",
                "初至京师，与太子宾客贺知童遇于紫极宮（即玄元庙）。贺既奇其姿，复赏其文，谓其诗“可以泣鬼神”，并呼白为“谪仙人”。复荐之于朝。",
                "玄宗召见于金銮殿，异礼有加，命待诏翰林",
                "十月，玄宗幸温泉宫，诏命李白侍从，作《侍从游宿温泉宫作》"]],
        "poem":["《为宋中丞自荐表》","《南陵别儿童入京》","《侍从游宿温泉宫作》","《温泉侍从归逢故人》","《驾去温泉宫后赠杨山人》","《赠杨山人》"],
        "num":6
    }
    ,{	"time":"743",
        "event":["正月，安禄山入朝，玄宗宠待甚厚，谒见无时","时李林甫专政，公卿之进，有不出其门者，必以罪去之"],
        "libai":[["因与朝中奸佞之辈不合，遂遭谗谤，玄宗疏之"],["#"]],
        "poem":[],
        "num":0
    
    }
    ,{	"time":"744",
        "event":["正月，贺知章请度为道士，玄宗赐还乡，遣左右相以下饯别于长乐坡",
                "玄宗以天下无事，欲高居无为，政事悉委李林甫"
                ],
        "libai":[["春正月，送贺知章归越，《送贺监归四明应制》"],
                ["自知不为朝廷亲近所容，遂于三月上书请还山。玄宗以其 “非廊庙器”，賜金谴之",
                "临行赋诗，悲愤不平，揮泪出长安，作《初出金门咏壁上鹦鹉》"]],
        "poem":["《送贺监归四明应制》","《朝下过卢郎中叙旧游》","《翰林读书言怀》","《同王昌龄送族弟襄归桂阳》",
            "《送裴十八图南归嵩山》","《设辟邪伎鼓吹雉子斑曲辞》","《初出金门咏壁上鹦鹉》","《还山留别金门知己》",
            "《古风之二十二》","《金门答苏秀才》","《赠郭将军》","《送族弟绾从军安西》","《送祝八之江东》",
            "《送窦司马贬宜春》","《白云歌送刘十六归山》","《望终南山寄紫阁隐者》","《下终南山过斛斯山人宿置酒》",
            "《古风之八》","《古风之三十六》","《古风之三十七》","《古风之三十九》","《古风之四十四》","《古风之四十六》",
            "《古风之四十九》","《古风之五十六》"],
        "num":25
    
    }
    ,{	"time":"746",
        "event":["李林甫欲尽除不附己者，重用酷吏吉温、罗希奭，屡兴冤狱，时人谓之“罗钳吉网”"],
        "libai":[["秋，疾瘳，又游于鲁郡，借诗讥评朝政，作《鲁郡尧祠送窦明府薄华还西京》"]],
        "poem":["《鲁郡尧祠送窦明府薄华还西京》"],
        "num":1
    
    }
    ,{"time":"747",
        "event":["正月，李林甫使罗希奭等杖杀北海太守李邕、淄川太守裴敦复"],
        "libai":[["冬，返至金陵。闻李邕、襄敦复被害事，不胜悲愤，初赋 《夷则格上白鸠拂舞辞》以讽其事"]],
        "poem":["《夷则格上白鸠拂舞辞》"],
        "num":1
    
    }
    ,{"time":"749",
        "event":["六月，玄宗命哥舒翰帅大兵攻石堡城，唐士卒死者数万人，果如王忠嗣之言。哥舒翰加摄御史大夫，王忠嗣抑郁而死"],
        "libai":[["冬，返至金陵。闻李邕、襄敦复被害事，不胜悲愤，初赋 《夷则格上白鸠拂舞辞》以讽其事"]],
        "poem":["《古风之六》","《古风之十四》"],
        "num":2
    
    }
    ,{"time":"751",
        "event":["高仙芝攻大食国，深入七百里，与战，大败，士卒死亡略尽"],
        "libai":[["虽身在江湖，仍未能忘情于功名，竟欲拂剑而起，收奇勋于沙漠，作《赠何七判官昌浩》"]],
        "poem":["《赠何七判官昌浩》"],
        "num":1
    
    }
    ,{"time":"752",
        "event":["750年十二月，安西四镇节度使高仙芝伪与石国约和，引兵袭之，虏其王及部众以归，悉杀其老弱，所得珍宝，皆入其家",
            "751年二月，安禄山兼河东节度使，禄山既领三镇（平卢、范阳、河东），有兵二十余万，几为天下兵力之半，日益骄恣，见玄宗年高，又见武备松弛，遂有轻中国之心，潜蓄异志。然斯时“势已盛而逆未露”"],
        "libai":[["初遇边地战事，赋《出自蓟北门行》。有灭虏报国之意","在边地习骑射","未几，识边地战争之真相，情绪遂转为怨愤。作《幽州胡马客歌》"],
                ["目击安禄山跋扈之状，心甚忧之，但无能为力，只有登燕昭王黄金台遗址，一洒忧国忧民之泪"]],
        "poem":["《出自蓟北门行》","《幽州胡马客歌》","《北风行》"],
        "num":3
    
    }
    ,{"time":"753",
        "event":["751年二月，安禄山兼河东节度使，禄山既领三镇（平卢、范阳、河东），有兵二十余万，几为天下兵力之半，日益骄恣，见玄宗年高，又见武备松弛，遂有轻中国之心，潜蓄异志。然斯时“势已盛而逆未露”"],
        "libai":[["幽州之行归来，深感危机严重，而又无能为力，唯有高举远引，以避祸乱，临行之际，复又感慨万端，作《留别曹南群官之江南》"]],
        "poem":["《留别曹南群官之江南》"],
        "num":1
    
    }
    ,{"time":"755",
        "event":["十一月，安禄山发所部兵及同罗、奚、契丹凡十五万众，号二十万，反于范阳，引兵而南，陷河北诸郡"],
        "libai":[["闻乱作，门人武谔来访，许北去鲁中，接子女南来，白赋诗以赠。见《赠武十七谔》","既以子女事托武诲，遂自往宋城接宗氏。作《北上行》"]],
        "poem":["《赠武十七谔》","《北上行》"],
        "num":2
    
    }
    ,{"time":"756",
        "event":["755年十一月，安禄山发所部兵及同罗、奚、契丹凡十五万众，号二十万，反于范阳，引兵而南，陷河北诸郡",
                "安史之乱初起之时，玄宗曾下亲征之制，并命太子监国，后为杨国忠及杨氏姊妹所阻，事遂寝",
                "正月，安禄山在洛阳，称大燕皇帝",
                "五月，郭子仪、李光弼大破史思明，复河北十余郡，安禄山遂有后顾之忧",
                "六月九日，哥舒翰与贼将崔乾祐战于灵宝，大败。贼入潼关，哥舒翰被擒，降贼；六月甲午（二十日）玄宗奔蜀。丙申（十四日）行至马嵬驿，兵变，杀杨国忠。玄宗被迫缢杀杨贵妃"],
        "libai":[["岁初，携宗氏南奔，作《奔亡道中五首》"],
                ["春在当涂。闻玄宗将亲征安禄山。甚喜。见《春于姑熟送赵四流炎方序》"],
                ["旋闻洛阳失陷，中原横溃，乃自当涂返宣城，将避地剡中。作《经乱后将避地剡中，留赠崔宣城》","旋到溧阳。与张旭相遇，饮于酒楼，感时伤事，赋《猛虎行》"],
                ["闻郭子仪、李光弼河北大捷，又返金陵。作《为吴王谢责迟赴行在表》"],
                ["秋，闻贼破潼关，玄宗奔蜀，遂沿江而西，入庐山，隐于屏风叠。作《赠王判官，时余归隐居庐山屏风叠》","岁暮，永王璘辟书数至。白几经犹豫，终于决定下山入幕。 作《与贾少公书》"]],
        "poem":["《奔亡道中五首》","《春于姑熟送赵四流炎方序》","《经乱后将避地剡中，留赠崔宣城》","《猛虎行》","《赠溧阳宋少府陟》","《扶风豪士歌》","《古风之十九》",
                "《为吴王谢责迟赴行在表》","《赠王判官，时余归隐居庐山屏风叠》","《与贾少公书》","《别内赴征》"],
        "num":11
    
    }
    ,{"time":"757",
        "event":["永王璘军次寻阳，旋进至当涂，遇阻，杀其守将，并降其余。江淮大震。淮南节度使高适与来瑱、韦陟发兵讨之”",
                "二月戊戌（初九日），永王璘兵败于丹阳",
                "十月，肃宗返长安"],
        "libai":[["以为璘出师东巡是奉朝廷之命，旨在“救河南”，“扫胡尘”，一清中原，遂作诗以颂之，并欲藉之立功报国。作《永王东巡歌十一首》"],
                ["永王璘兵败于丹阳，白自丹阳南奔。作《南奔书怀》","又西逃至舒州，避于太湖县之司空山（其地南距寻阳约百里）作《避地司空原言怀》","终以从璘事长流夜郎，作《流夜郎闻酺不预》","旋陷寻阳狱中。多次上书申诉求援。作《狱中上崔相涣》"],
                ["十二月，闻玄宗返长安，作《上皇西巡南京歌十首》以刺之"]],
        "poem":["《永王东巡歌十一首》","《在水军宴赠幕府诸侍御》","《流夜郎闻酺不预》","《南奔书怀》","《避地司空原言怀》","《狱中上崔相涣》","《系寻阳上崔相涣三首》","《上崔相百忧草》","《万愤词投魏郎中》","《送张秀才谒高中丞》",
        "《上皇西巡南京歌十首》"],
        "num":11
    
    }
    ,{"time":"758",
        "event":["757年以从璘事长流夜郎"],
        "libai":[["流夜郎，自寻阳首途。作《流夜郎，永华寺寄浔阳群官》","与其妻宗氏别，赋《双燕离》诗一首","其妻弟宗璟伴送白至乌江，白赋诗留别。见《窜夜郎于乌江留别宗十六璟》","春末夏初，在流放途中，行至西塞驿，作《流夜郎至西塞驿寄裴隐》","五月，在流放途中，行至江夏。见《张相公出镇荆州》",
                "登黄鹤楼，望鹦鹉洲，赋诗言怀，借祢衡故事，大舒愤懑。作《望鹦鹉洲怀祢衡》","八月，在沔洲汉阳县游南湖。作《泛沔洲城南郎官湖并序》","秋，在流放途中，行至江陵。作《赠别郑判官》","冬，入三峡。作《上三峡》"]],
        "poem":["《流夜郎，永华寺寄浔阳群官》","《双燕离》","《窜夜郎于乌江留别宗十六璟》","《流夜郎至西塞驿寄裴隐》","《张相公出镇荆州》","《望鹦鹉洲怀祢衡》","《泛沔洲城南郎官湖并序》","《赠别郑判官》","《上三峡》",
                "《流夜郎赠辛判官》","《寄王汉阳》","《留别龚处士》","《赠易秀才》","《流夜郎题葵叶》","《放后遇恩不霑》"],
        "num":15
    
    }
    ,{"time":"759",
        "event":["757年以从璘事长流夜郎",
                "八月，襄州将康楚元、张嘉延据州作乱，九月，袭荆州，十一月聚众至万人，十二月乱平"],
        "libai":[["春在流途。作《南流夜郎寄内》","三月，到白帝，遇赦。喜出望外，立返江陵。作《早发白帝城》"],
                ["九月，遇荆州乱起，遂逗留至冬。作《九日登巴陵置酒望洞庭水军》"]],
        "poem":["《南流夜郎寄内》","《早发白帝城》","《九日登巴陵置酒望洞庭水军》","《荆州贼乱临洞庭言怀作》","《赠别舍人弟台卿之江南》","《秋夕书怀》","《泽畔吟序》","《草书歌行》","《门有车马客行》"],
        "num":9
    
    }
    ,{"time":"761",
        "event":["润州副使李藏用平刘展乱",
            "五月，李光弼拜太尉，充河南副元帅，都统八道行营节度，出镇临淮。时贼势复炽，将士皆惧，请南保扬州。光弼径赴徐州（即彭城郡）以镇之，败史朝义。旋赴浙东镇压袁晁农民起义"],
        "libai":[["参与饯别润州副使李藏用为平刘展之乱移军广陵，为作序"],
        ["闻史朝义贼焰复炽，李光弼出镇临淮，白又欲立功报国，并一雪“会潛之耻”，遂请缨入幕，但因病半道而还，不胜怅恨，赋诗纪之。作《闻李太尉大举秦兵百万出征东南，懦夫请缨，冀申一割之用，半道病还，留别金陵崔侍御十九韵》"]],
        "poem":["《闻李太尉大举秦兵百万出征东南，懦夫请缨，冀申一割之用，半道病还，留别金陵崔侍御十九韵》"],
        "num":1
    
    }
]